naive_svg/__init__.py
naive_svg/__main__.py
naive_svg/_core.cpython-311-x86_64-linux-gnu.so
naive_svg/_core.pyi
naive_svg/geojson2svg.py
naive_svg/py.typed
naive_svg-0.1.1.dist-info/METADATA
naive_svg-0.1.1.dist-info/WHEEL
naive_svg-0.1.1.dist-info/RECORD
naive_svg-0.1.1.dist-info/licenses/LICENSE
