Metadata-Version: 2.2
Name: naive_svg
Version: 0.1.1
Summary: naive svg writer
Author-Email: district10 <dvorak4tzx@gmail.com>
Classifier: Development Status :: 4 - Beta
Classifier: License :: OSI Approved :: MIT License
Classifier: Programming Language :: Python :: 3 :: Only
Classifier: Programming Language :: Python :: 3.7
Classifier: Programming Language :: Python :: 3.8
Classifier: Programming Language :: Python :: 3.9
Classifier: Programming Language :: Python :: 3.10
Classifier: Programming Language :: Python :: 3.11
Classifier: Programming Language :: Python :: 3.12
Project-URL: Homepage, https://github.com/cubao/pybind11-naive-svg
Requires-Python: >=3.7
Requires-Dist: numpy
Requires-Dist: pybind11_geobuf
Provides-Extra: test
Requires-Dist: pytest; extra == "test"
